elementally/__init__.py
elementally-0.2.dist-info/LICENSE
elementally-0.2.dist-info/METADATA
elementally-0.2.dist-info/WHEEL
elementally-0.2.dist-info/top_level.txt
elementally-0.2.dist-info/RECORD
